README.md
setup.py
TPUnityAI.egg-info/PKG-INFO
TPUnityAI.egg-info/SOURCES.txt
TPUnityAI.egg-info/dependency_links.txt
TPUnityAI.egg-info/requires.txt
TPUnityAI.egg-info/top_level.txt
tp/__init__.py
tp/debug/__init__.py
tp/debug/api.py