Metadata-Version: 2.1
Name: TPUnityAI
Version: 0.2
Summary: Python API for Unity.
Home-page: https://github.com/Byuan3/tp_python_api
Author: Li-Harry-Fa22-2
Author-email: test@test.com
License: Apache License 2.0
Platform: UNKNOWN
